{
  "generator-jhipster": {
    "applicationType": "monolith",
    "gitHubOrganization": "TheDoctor-95",
    "baseName": "FuryMusicPrime",
    "packageName": "com.fury",
    "serverPort": 8080,
    "serviceDiscoveryType": false,
    "authenticationType": "jwt",
    "uaaBaseName": "../uaa",
    "hibernateCache": "ehcache",
    "clusteredHttpSession": false,
    "websocket": false,
    "databaseType": "sql",
    "devDatabaseType": "mysql",
    "prodDatabaseType": "mysql",
    "searchEngine": false,
    "enableSwaggerCodegen": false,
    "messageBroker": false,
    "buildTool": "maven",
    "enableSocialSignIn": true,
    "useSass": false,
    "clientPackageManager": "yarn",
    "testFrameworks": [],
    "enableTranslation": true,
    "nativeLanguage": "en",
    "languages": [
      "ca",
      "en",
      "es"
    ],
    "clientFramework": "angularX",
    "jhipsterVersion": "4.10.2",
    "packageFolder": "com/fury",
    "jwtSecretKey": "45f03020de6c8c25f7cae89ae03234556d733d8a",
    "jhiPrefix": "jhi"
  }
}